calista_timer/Timer.py
calista_timer/calista.py
calista_timer-1.1.dist-info/LICENSE
calista_timer-1.1.dist-info/METADATA
calista_timer-1.1.dist-info/WHEEL
calista_timer-1.1.dist-info/entry_points.txt
calista_timer-1.1.dist-info/RECORD
