Metadata-Version: 2.3
Name: calista-timer
Version: 1.1
Summary: Simple terminal based timer
License: MIT
Author: Vall-333
Author-email: vallg8343@proton.me
Requires-Python: >=3.13
Classifier: License :: OSI Approved :: MIT License
Classifier: Programming Language :: Python :: 3
Classifier: Programming Language :: Python :: 3.13
Requires-Dist: click (>=8.2.1,<9.0.0)
